GHL/__init__.py
GHL/ghlFunctions.py
GHLPy-0.0.3.dist-info/METADATA
GHLPy-0.0.3.dist-info/WHEEL
GHLPy-0.0.3.dist-info/top_level.txt
GHLPy-0.0.3.dist-info/RECORD
