Metadata-Version: 2.1
Name: GHLPy
Version: 0.0.3
Summary: A basic python wrapper for gohighlevel
Home-page: UNKNOWN
Author: Nyzex
Author-email: <nyrize025@gmail.com>
License: UNKNOWN
Keywords: python,ghl,gohighlevel,api,wrapper
Platform: UNKNOWN
Classifier: Development Status :: 1 - Planning
Classifier: Intended Audience :: Developers
Classifier: Programming Language :: Python :: 3
Classifier: Operating System :: Unix
Classifier: Operating System :: MacOS :: MacOS X
Classifier: Operating System :: Microsoft :: Windows
Requires-Dist: python-dateutil
Requires-Dist: requests
